autopep695/__init__.py
autopep695/__main__.py
autopep695/aliases.py
autopep695/analyzer.py
autopep695/base.py
autopep695/check.py
autopep695/cli.py
autopep695/errors.py
autopep695/format.py
autopep695/helpers.py
autopep695/py.typed
autopep695/symbols.py
autopep695/ux.py
autopep695-1.1.4.dist-info/entry_points.txt
autopep695-1.1.4.dist-info/LICENSE
autopep695-1.1.4.dist-info/WHEEL
autopep695-1.1.4.dist-info/METADATA
autopep695-1.1.4.dist-info/RECORD
