Metadata-Version: 2.1
Name: autopep695
Version: 1.1.4
Summary: Automatically upgrade to the new type syntax introduced in PEP 695 using a single command
Author-email: yowoda <yodarlswitch@gmail.com>
Requires-Python: >=3.9
Classifier: License :: OSI Approved :: MIT License
Classifier: Topic :: Software Development :: Libraries
Classifier: Programming Language :: Python :: 3.9
Classifier: Programming Language :: Python :: 3.10
Classifier: Programming Language :: Python :: 3.11
Classifier: Programming Language :: Python :: 3.12
Requires-Dist: libcst>=1.4.0
Requires-Dist: colorama>=0.4.6, <1
Requires-Dist: typing-extensions>=4.12.2, <5
Requires-Dist: nox==2024.10.9 ; extra == "dev"
Requires-Dist: towncrier==24.8.0 ; extra == "dev.changelog"
Requires-Dist: ruff>=0.6.3, <0.7 ; extra == "dev.format"
Requires-Dist: flit==3.9.0 ; extra == "dev.release"
Requires-Dist: slotscheck>=0.19.0, <1 ; extra == "dev.slotscheck"
Requires-Dist: pytest>=8.3.3, <9 ; extra == "dev.test"
Requires-Dist: pyright==1.1.384 ; extra == "dev.typecheck"
Project-URL: Homepage, https://github.com/yowoda/autopep695
Project-URL: Repository, https://github.com/yowoda/autopep695
Provides-Extra: dev
Provides-Extra: dev.changelog
Provides-Extra: dev.format
Provides-Extra: dev.release
Provides-Extra: dev.slotscheck
Provides-Extra: dev.test
Provides-Extra: dev.typecheck
